bwtv.py
bundlewrap_teamvault-3.1.5.dist-info/LICENSE
bundlewrap_teamvault-3.1.5.dist-info/METADATA
bundlewrap_teamvault-3.1.5.dist-info/WHEEL
bundlewrap_teamvault-3.1.5.dist-info/top_level.txt
bundlewrap_teamvault-3.1.5.dist-info/RECORD
