Metadata-Version: 2.1
Name: bundlewrap-teamvault
Version: 3.1.5
Summary: Access TeamVault secrets from BundleWrap
Author: Torsten Rehn
Author-email: torsten@rehn.email
License: GPLv3
Keywords: configuration,config,management
Classifier: Development Status :: 5 - Production/Stable
Classifier: Intended Audience :: System Administrators
Classifier: License :: OSI Approved :: GNU General Public License v3 (GPLv3)
Classifier: Natural Language :: English
Classifier: Operating System :: POSIX :: Linux
Classifier: Programming Language :: Python
Classifier: Programming Language :: Python :: 3.7
Classifier: Programming Language :: Python :: 3.8
Classifier: Programming Language :: Python :: 3.9
Classifier: Programming Language :: Python :: 3.10
Classifier: Programming Language :: Python :: 3.11
Classifier: Topic :: Software Development :: Libraries :: Python Modules
Classifier: Topic :: System :: Installation/Setup
Classifier: Topic :: System :: Systems Administration
License-File: LICENSE
Requires-Dist: bundlewrap >=4.0.0
Requires-Dist: passlib
Requires-Dist: requests >=1.0.0
